{
	"name": "Room_34",
	"layers": [
		{
			"name": "fondo",
			"overriden": 0,
			"subLayers": [],
			"instances": [
				{
					"type": "fondo_mundo_4_corto",
					"properties": {
						"initially-visible": true,
						"initial-animation": "Animation 1",
						"initial-frame": 0,
						"enable-collisions": true,
						"live-preview": false
					},
					"uid": 9166,
					"instanceVariables": {},
					"behaviors": {},
					"world": {
						"x": 427,
						"y": 241,
						"width": 946,
						"height": 485.00000000000006,
						"originX": 0.5,
						"originY": 0.5,
						"color": [
							1,
							1,
							1,
							1
						],
						"angle": 0,
						"zElevation": 0
					}
				},
				{
					"type": "atasco_saltarines_IZQ",
					"properties": {
						"initially-visible": false,
						"initial-animation": "Default",
						"initial-frame": 0,
						"enable-collisions": true,
						"live-preview": false
					},
					"uid": 9167,
					"instanceVariables": {},
					"behaviors": {},
					"world": {
						"x": 32,
						"y": 107,
						"width": 14,
						"height": -134,
						"originX": 0.5,
						"originY": 0.5,
						"color": [
							1,
							1,
							1,
							1
						],
						"angle": 0,
						"zElevation": 0
					}
				},
				{
					"type": "FONDO_M3",
					"properties": {
						"initially-visible": true,
						"tile-width": 32,
						"tile-height": 32,
						"tile-x-offset": 0,
						"tile-y-offset": 0,
						"tile-x-spacing": 0,
						"tile-y-spacing": 0,
						"tile-x-drawing-offset": 0,
						"tile-y-drawing-offset": 0,
						"drawing-mode": "top-to-right"
					},
					"uid": 9168,
					"instanceVariables": {},
					"behaviors": {},
					"ownData": {
						"tilemapData": {
							"width": 33,
							"height": 19,
							"max-width": 146,
							"max-height": 106,
							"data": "19x2,87x0,19x2,87x0,4x2,121,141,13x2,87x0,4x2,122,142,8x2,121,141,3x2,87x0,4x2,123,143,8x2,122,142,3x2,87x0,14x2,123,143,3x2,274,292,85x0,19x2,87x0,3x2,121,141,14x2,87x0,3x2,122,142,14x2,87x0,3x2,123,143,4x2,121,141,8x2,87x0,9x2,122,142,8x2,87x0,9x2,123,143,8x2,87x0,10x2,50,5x70,3x2,87x0,10x2,51,5x71,3x2,87x0,10x2,51,5x71,3x2,87x0,10x2,51,5x71,3x2,87x0,10x2,52,5x72,3x2,87x0,12x2,121,141,5x2,87x0,7x2,121,141,3x2,122,142,5x2,87x0,7x2,122,142,3x2,123,143,5x2,87x0,7x2,123,143,2,50,7x70,2,87x0,10x2,51,7x71,2,87x0,10x2,51,7x71,2,87x0,10x2,51,7x71,2,87x0,7x2,121,141,2,52,7x72,2,87x0,7x2,122,142,10x2,87x0,3x2,121,141,2x2,123,143,10x2,87x0,3x2,122,142,5x2,121,141,7x2,87x0,3x2,123,143,5x2,122,142,7x2,87x0,10x2,123,143,7x2,87x0,10x2,123,143,7x2,87x0,19x2,11x0,22,75x0,19x2,11x0,22,105x0,22,105x0,22,105x0,22,105x0,22,105x0,22,105x0,22,105x0,22,105x0,22,105x0,22,105x0,22,105x0,22,105x0,22,105x0,22,105x0,22,105x0,22,10463x0"
						},
						"tile-width": 32,
						"tile-height": 32,
						"tile-x-offset": 0,
						"tile-y-offset": 0,
						"tile-x-spacing": 0,
						"tile-y-spacing": 0
					},
					"world": {
						"x": -116,
						"y": -55,
						"width": 1067,
						"height": 623,
						"originX": 0,
						"originY": 0,
						"color": [
							1,
							1,
							1,
							1
						],
						"zElevation": 0
					}
				},
				{
					"type": "puerta",
					"properties": {
						"initially-visible": false,
						"initial-animation": "cerrada",
						"initial-frame": 0,
						"enable-collisions": true,
						"live-preview": false
					},
					"uid": 9169,
					"instanceVariables": {
						"abierta": false,
						"PANTALLA": 34,
						"sigueinte_nivel": ""
					},
					"behaviors": {},
					"world": {
						"x": 83.22798454579055,
						"y": 191.87264915556287,
						"width": 78,
						"height": 90,
						"originX": 0.5,
						"originY": 1,
						"color": [
							1,
							1,
							1,
							1
						],
						"angle": 0,
						"zElevation": 0
					}
				},
				{
					"type": "puerta_M3",
					"properties": {
						"initially-visible": true,
						"initial-animation": "cerrada",
						"initial-frame": 0,
						"enable-collisions": true,
						"live-preview": false
					},
					"uid": 9170,
					"instanceVariables": {
						"abierta": false,
						"PANTALLA": 11
					},
					"behaviors": {},
					"world": {
						"x": 85,
						"y": 192,
						"width": 78,
						"height": 90,
						"originX": 0.5,
						"originY": 1,
						"color": [
							1,
							1,
							1,
							1
						],
						"angle": 0,
						"zElevation": 0
					}
				}
			],
			"sid": 872773314294304,
			"effectTypes": [],
			"isInitiallyVisible": true,
			"isInitiallyInteractive": true,
			"color": [
				1,
				1,
				1,
				1
			],
			"backgroundColor": [
				1,
				1,
				1,
				1
			],
			"isTransparent": false,
			"parallaxX": 1,
			"parallaxY": 1,
			"scaleRate": 1,
			"forceOwnTexture": false,
			"renderingMode": "3d",
			"drawOrder": "z-order",
			"useRenderCells": false,
			"blendMode": "normal",
			"zElevation": 0,
			"global": false
		},
		{
			"name": "decoracion",
			"overriden": 0,
			"subLayers": [],
			"instances": [
				{
					"type": "Mundo_4_pilar_de2",
					"properties": {
						"initially-visible": true,
						"origin": "top-left",
						"wrap-horizontal": "repeat",
						"wrap-vertical": "repeat",
						"image-offset-x": 0,
						"image-offset-y": 0,
						"image-scale-x": 1,
						"image-scale-y": 1,
						"image-angle": 0
					},
					"uid": 9171,
					"instanceVariables": {},
					"behaviors": {},
					"world": {
						"x": 442,
						"y": 214,
						"width": 64,
						"height": 265,
						"originX": 0,
						"originY": 0,
						"color": [
							1,
							1,
							1,
							1
						],
						"angle": 0,
						"zElevation": 0
					}
				},
				{
					"type": "Mundo_4_contrafuerte_dcha",
					"properties": {
						"initially-visible": true,
						"initial-animation": "Default",
						"initial-frame": 0,
						"enable-collisions": true,
						"live-preview": false
					},
					"uid": 9172,
					"instanceVariables": {},
					"behaviors": {},
					"world": {
						"x": 416,
						"y": 75,
						"width": 38,
						"height": 38,
						"originX": 0.5,
						"originY": 0.5,
						"color": [
							1,
							1,
							1,
							1
						],
						"angle": 0,
						"zElevation": 0
					}
				},
				{
					"type": "Mundo_4_contrafuerte_iz",
					"properties": {
						"initially-visible": true,
						"initial-animation": "Default",
						"initial-frame": 0,
						"enable-collisions": true,
						"live-preview": false
					},
					"uid": 9173,
					"instanceVariables": {},
					"behaviors": {},
					"world": {
						"x": 442,
						"y": 75,
						"width": 38,
						"height": 38,
						"originX": 0.5,
						"originY": 0.5,
						"color": [
							1,
							1,
							1,
							1
						],
						"angle": 0,
						"zElevation": 0
					}
				},
				{
					"type": "Mundo_4_contrafuerte_ex_iz",
					"properties": {
						"initially-visible": true,
						"origin": "top-left",
						"wrap-horizontal": "repeat",
						"wrap-vertical": "repeat",
						"image-offset-x": 0,
						"image-offset-y": 0,
						"image-scale-x": 1,
						"image-scale-y": 1,
						"image-angle": 0
					},
					"uid": 9174,
					"instanceVariables": {},
					"behaviors": {},
					"world": {
						"x": 423,
						"y": 94,
						"width": 12,
						"height": 112,
						"originX": 0,
						"originY": 0,
						"color": [
							1,
							1,
							1,
							1
						],
						"angle": 0,
						"zElevation": 0
					}
				},
				{
					"type": "Mundo_4_contrafuerte_dcha",
					"properties": {
						"initially-visible": true,
						"initial-animation": "Default",
						"initial-frame": 0,
						"enable-collisions": true,
						"live-preview": false
					},
					"uid": 9175,
					"instanceVariables": {},
					"behaviors": {},
					"world": {
						"x": 641,
						"y": 75,
						"width": 38,
						"height": 38,
						"originX": 0.5,
						"originY": 0.5,
						"color": [
							1,
							1,
							1,
							1
						],
						"angle": 0,
						"zElevation": 0
					}
				},
				{
					"type": "Mundo_4_contrafuerte_iz",
					"properties": {
						"initially-visible": true,
						"initial-animation": "Default",
						"initial-frame": 0,
						"enable-collisions": true,
						"live-preview": false
					},
					"uid": 9176,
					"instanceVariables": {},
					"behaviors": {},
					"world": {
						"x": 667,
						"y": 75,
						"width": 38,
						"height": 38,
						"originX": 0.5,
						"originY": 0.5,
						"color": [
							1,
							1,
							1,
							1
						],
						"angle": 0,
						"zElevation": 0
					}
				},
				{
					"type": "Mundo_4_contrafuerte_ex_iz",
					"properties": {
						"initially-visible": true,
						"origin": "top-left",
						"wrap-horizontal": "repeat",
						"wrap-vertical": "repeat",
						"image-offset-x": 0,
						"image-offset-y": 0,
						"image-scale-x": 1,
						"image-scale-y": 1,
						"image-angle": 0
					},
					"uid": 9177,
					"instanceVariables": {},
					"behaviors": {},
					"world": {
						"x": 648,
						"y": 94,
						"width": 12,
						"height": 112,
						"originX": 0,
						"originY": 0,
						"color": [
							1,
							1,
							1,
							1
						],
						"angle": 0,
						"zElevation": 0
					}
				},
				{
					"type": "Mundo_4_contrafuerte_iz_sin",
					"properties": {
						"initially-visible": true,
						"initial-animation": "Default",
						"initial-frame": 0,
						"enable-collisions": true,
						"live-preview": false
					},
					"uid": 9178,
					"instanceVariables": {},
					"behaviors": {},
					"world": {
						"x": 38,
						"y": 268,
						"width": 38,
						"height": 38,
						"originX": 0.5,
						"originY": 0.5,
						"color": [
							1,
							1,
							1,
							1
						],
						"angle": 0,
						"zElevation": 0
					}
				},
				{
					"type": "Mundo_4_contrafuerte_iz_sin",
					"properties": {
						"initially-visible": true,
						"initial-animation": "Default",
						"initial-frame": 0,
						"enable-collisions": true,
						"live-preview": false
					},
					"uid": 9179,
					"instanceVariables": {},
					"behaviors": {},
					"world": {
						"x": 38,
						"y": 76,
						"width": 38,
						"height": 38,
						"originX": 0.5,
						"originY": 0.5,
						"color": [
							1,
							1,
							1,
							1
						],
						"angle": 0,
						"zElevation": 0
					}
				},
				{
					"type": "Mundo_4_contrafuerte_dch_sin",
					"properties": {
						"initially-visible": true,
						"initial-animation": "Default",
						"initial-frame": 0,
						"enable-collisions": true,
						"live-preview": false
					},
					"uid": 9180,
					"instanceVariables": {},
					"behaviors": {},
					"world": {
						"x": 817,
						"y": 76,
						"width": 38,
						"height": 38,
						"originX": 0.5,
						"originY": 0.5,
						"color": [
							1,
							1,
							1,
							1
						],
						"angle": 0,
						"zElevation": 0
					}
				},
				{
					"type": "Mundo_4_cubo_gr_",
					"properties": {
						"initially-visible": true,
						"initial-animation": "Default",
						"initial-frame": 0,
						"enable-collisions": false,
						"live-preview": false
					},
					"uid": 9181,
					"instanceVariables": {},
					"behaviors": {},
					"world": {
						"x": 264,
						"y": 108,
						"width": 64,
						"height": 64,
						"originX": 0.5,
						"originY": 0.5,
						"color": [
							1,
							1,
							1,
							1
						],
						"angle": 0,
						"zElevation": 0
					}
				},
				{
					"type": "Mundo_4_contrafuerte_dcha",
					"properties": {
						"initially-visible": true,
						"initial-animation": "Default",
						"initial-frame": 0,
						"enable-collisions": true,
						"live-preview": false
					},
					"uid": 9182,
					"instanceVariables": {},
					"behaviors": {},
					"world": {
						"x": 192,
						"y": 75,
						"width": 38,
						"height": 38,
						"originX": 0.5,
						"originY": 0.5,
						"color": [
							1,
							1,
							1,
							1
						],
						"angle": 0,
						"zElevation": 0
					}
				},
				{
					"type": "Mundo_4_contrafuerte_iz",
					"properties": {
						"initially-visible": true,
						"initial-animation": "Default",
						"initial-frame": 0,
						"enable-collisions": true,
						"live-preview": false
					},
					"uid": 9183,
					"instanceVariables": {},
					"behaviors": {},
					"world": {
						"x": 218,
						"y": 75,
						"width": 38,
						"height": 38,
						"originX": 0.5,
						"originY": 0.5,
						"color": [
							1,
							1,
							1,
							1
						],
						"angle": 0,
						"zElevation": 0
					}
				},
				{
					"type": "Mundo_4_contrafuerte_ex_iz",
					"properties": {
						"initially-visible": true,
						"origin": "top-left",
						"wrap-horizontal": "repeat",
						"wrap-vertical": "repeat",
						"image-offset-x": 0,
						"image-offset-y": 0,
						"image-scale-x": 1,
						"image-scale-y": 1,
						"image-angle": 0
					},
					"uid": 9184,
					"instanceVariables": {},
					"behaviors": {},
					"world": {
						"x": 199,
						"y": 94,
						"width": 12,
						"height": 112,
						"originX": 0,
						"originY": 0,
						"color": [
							1,
							1,
							1,
							1
						],
						"angle": 0,
						"zElevation": 0
					}
				},
				{
					"type": "Mundo_4_cubo_gr_7",
					"properties": {
						"initially-visible": true,
						"initial-animation": "Default",
						"initial-frame": 0,
						"enable-collisions": false,
						"live-preview": false
					},
					"uid": 9185,
					"instanceVariables": {},
					"behaviors": {},
					"world": {
						"x": 363,
						"y": 107,
						"width": 64,
						"height": 64,
						"originX": 0.5,
						"originY": 0.5,
						"color": [
							1,
							1,
							1,
							1
						],
						"angle": 0,
						"zElevation": 0
					}
				},
				{
					"type": "Mundo_4_cubo_gr_2",
					"properties": {
						"initially-visible": true,
						"initial-animation": "Default",
						"initial-frame": 0,
						"enable-collisions": false,
						"live-preview": false
					},
					"uid": 9186,
					"instanceVariables": {},
					"behaviors": {},
					"world": {
						"x": 494,
						"y": 107,
						"width": 64,
						"height": 64,
						"originX": 0.5,
						"originY": 0.5,
						"color": [
							1,
							1,
							1,
							1
						],
						"angle": 0,
						"zElevation": 0
					}
				},
				{
					"type": "Mundo_4_cubo_gr_3",
					"properties": {
						"initially-visible": true,
						"initial-animation": "Default",
						"initial-frame": 0,
						"enable-collisions": false,
						"live-preview": false
					},
					"uid": 9187,
					"instanceVariables": {},
					"behaviors": {},
					"world": {
						"x": 593,
						"y": 107,
						"width": 64,
						"height": 64,
						"originX": 0.5,
						"originY": 0.5,
						"color": [
							1,
							1,
							1,
							1
						],
						"angle": 0,
						"zElevation": 0
					}
				},
				{
					"type": "Mundo_4_cenefa_esquina_top_iz",
					"properties": {
						"initially-visible": true,
						"initial-animation": "Default",
						"initial-frame": 0,
						"enable-collisions": false,
						"live-preview": false
					},
					"uid": 9188,
					"instanceVariables": {},
					"behaviors": {},
					"world": {
						"x": 47,
						"y": 298,
						"width": 23,
						"height": 25,
						"originX": 0.4782608695652174,
						"originY": 0.48,
						"color": [
							1,
							1,
							1,
							1
						],
						"angle": 0,
						"zElevation": 0
					}
				},
				{
					"type": "Mundo_4_cenefa_hor_",
					"properties": {
						"initially-visible": true,
						"initial-animation": "Default",
						"initial-frame": 0,
						"enable-collisions": false,
						"live-preview": false
					},
					"uid": 9189,
					"instanceVariables": {},
					"behaviors": {},
					"world": {
						"x": 75,
						"y": 294,
						"width": 32,
						"height": 16,
						"originX": 0.5,
						"originY": 0.5,
						"color": [
							1,
							1,
							1,
							1
						],
						"angle": 0,
						"zElevation": 0
					}
				},
				{
					"type": "Mundo_4_cenefa_hor_2",
					"properties": {
						"initially-visible": true,
						"initial-animation": "Default",
						"initial-frame": 0,
						"enable-collisions": false,
						"live-preview": false
					},
					"uid": 9190,
					"instanceVariables": {},
					"behaviors": {},
					"world": {
						"x": 107,
						"y": 294,
						"width": 32,
						"height": 16,
						"originX": 0.5,
						"originY": 0.5,
						"color": [
							1,
							1,
							1,
							1
						],
						"angle": 0,
						"zElevation": 0
					}
				},
				{
					"type": "Mundo_4_cenefa_esquina_topder",
					"properties": {
						"initially-visible": true,
						"initial-animation": "Default",
						"initial-frame": 0,
						"enable-collisions": false,
						"live-preview": false
					},
					"uid": 9191,
					"instanceVariables": {},
					"behaviors": {},
					"world": {
						"x": 134,
						"y": 298,
						"width": 23,
						"height": 25,
						"originX": 0.4782608695652174,
						"originY": 0.48,
						"color": [
							1,
							1,
							1,
							1
						],
						"angle": 0,
						"zElevation": 0
					}
				},
				{
					"type": "Mundo_4_cenefa_esquina_bot_iz",
					"properties": {
						"initially-visible": true,
						"initial-animation": "Default",
						"initial-frame": 0,
						"enable-collisions": false,
						"live-preview": false
					},
					"uid": 9192,
					"instanceVariables": {},
					"behaviors": {},
					"world": {
						"x": 47,
						"y": 354,
						"width": 23,
						"height": 23,
						"originX": 0.4782608695652174,
						"originY": 0.4782608695652174,
						"color": [
							1,
							1,
							1,
							1
						],
						"angle": 0,
						"zElevation": 0
					}
				},
				{
					"type": "Mundo_4_cenfa_esquina_bot_dcha",
					"properties": {
						"initially-visible": true,
						"initial-animation": "Default",
						"initial-frame": 0,
						"enable-collisions": false,
						"live-preview": false
					},
					"uid": 9193,
					"instanceVariables": {},
					"behaviors": {},
					"world": {
						"x": 134,
						"y": 353,
						"width": 23,
						"height": 23,
						"originX": 0.4782608695652174,
						"originY": 0.4782608695652174,
						"color": [
							1,
							1,
							1,
							1
						],
						"angle": 0,
						"zElevation": 0
					}
				},
				{
					"type": "Mundo_4_cenefa_ver_",
					"properties": {
						"initially-visible": true,
						"initial-animation": "Default",
						"initial-frame": 0,
						"enable-collisions": false,
						"live-preview": false
					},
					"uid": 9194,
					"instanceVariables": {},
					"behaviors": {},
					"world": {
						"x": 44,
						"y": 327,
						"width": 16,
						"height": 32,
						"originX": 0.5,
						"originY": 0.5,
						"color": [
							1,
							1,
							1,
							1
						],
						"angle": 0,
						"zElevation": 0
					}
				},
				{
					"type": "Mundo_4_cenefa_ver_",
					"properties": {
						"initially-visible": true,
						"initial-animation": "Default",
						"initial-frame": 0,
						"enable-collisions": false,
						"live-preview": false
					},
					"uid": 9195,
					"instanceVariables": {},
					"behaviors": {},
					"world": {
						"x": 138,
						"y": 327,
						"width": 16,
						"height": 32,
						"originX": 0.5,
						"originY": 0.5,
						"color": [
							1,
							1,
							1,
							1
						],
						"angle": 0,
						"zElevation": 0
					}
				},
				{
					"type": "Mundo_4_cenefa_hor_",
					"properties": {
						"initially-visible": true,
						"initial-animation": "Default",
						"initial-frame": 0,
						"enable-collisions": false,
						"live-preview": false
					},
					"uid": 9196,
					"instanceVariables": {},
					"behaviors": {},
					"world": {
						"x": 75,
						"y": 357,
						"width": 32,
						"height": 16,
						"originX": 0.5,
						"originY": 0.5,
						"color": [
							1,
							1,
							1,
							1
						],
						"angle": 0,
						"zElevation": 0
					}
				},
				{
					"type": "Mundo_4_cenefa_hor_2",
					"properties": {
						"initially-visible": true,
						"initial-animation": "Default",
						"initial-frame": 0,
						"enable-collisions": false,
						"live-preview": false
					},
					"uid": 9197,
					"instanceVariables": {},
					"behaviors": {},
					"world": {
						"x": 107,
						"y": 357,
						"width": 32,
						"height": 16,
						"originX": 0.5,
						"originY": 0.5,
						"color": [
							1,
							1,
							1,
							1
						],
						"angle": 0,
						"zElevation": 0
					}
				},
				{
					"type": "DECORACION_M1_14",
					"properties": {
						"initially-visible": true,
						"initial-animation": "Default",
						"initial-frame": 0,
						"enable-collisions": false,
						"live-preview": false
					},
					"uid": 9198,
					"instanceVariables": {},
					"behaviors": {},
					"world": {
						"x": 475,
						"y": 305,
						"width": 98.18018104622956,
						"height": 98.18018104622956,
						"originX": 0.5,
						"originY": 0.56383,
						"color": [
							0.7176470588235294,
							0.4823529411764706,
							0.4235294117647059,
							1
						],
						"angle": 0,
						"zElevation": 0
					}
				},
				{
					"type": "Mundo_4_torch_new",
					"properties": {
						"initially-visible": true,
						"initial-animation": "Animation 1",
						"initial-frame": 0,
						"enable-collisions": true,
						"live-preview": false
					},
					"uid": 9199,
					"instanceVariables": {},
					"behaviors": {},
					"world": {
						"x": 475,
						"y": 305,
						"width": 64,
						"height": 64,
						"originX": 0.5,
						"originY": 0.5,
						"color": [
							1,
							1,
							1,
							1
						],
						"angle": 0,
						"zElevation": 0
					}
				},
				{
					"type": "sierras",
					"properties": {
						"initially-visible": true,
						"initial-animation": "Default",
						"initial-frame": 0,
						"enable-collisions": true,
						"live-preview": false
					},
					"uid": 9200,
					"instanceVariables": {
						"velocidad": 2.5,
						"direccion": 0,
						"activa_TOPES": true,
						"IZQ_tope": 35,
						"DER_tope": 370,
						"UP_tope": 0,
						"DOWN_tope": 0
					},
					"behaviors": {
						"Rotate": {
							"properties": {
								"speed": 180,
								"acceleration": 0,
								"enabled": true,
								"live-preview": false
							}
						}
					},
					"world": {
						"x": 85,
						"y": 191,
						"width": 64,
						"height": 64,
						"originX": 0.5,
						"originY": 0.5,
						"color": [
							1,
							1,
							1,
							1
						],
						"angle": 0,
						"zElevation": 0
					}
				},
				{
					"type": "sierras",
					"properties": {
						"initially-visible": true,
						"initial-animation": "Default",
						"initial-frame": 0,
						"enable-collisions": true,
						"live-preview": false
					},
					"uid": 9201,
					"instanceVariables": {
						"velocidad": 2.5,
						"direccion": 0,
						"activa_TOPES": true,
						"IZQ_tope": 35,
						"DER_tope": 370,
						"UP_tope": 0,
						"DOWN_tope": 0
					},
					"behaviors": {
						"Rotate": {
							"properties": {
								"speed": 180,
								"acceleration": 0,
								"enabled": true,
								"live-preview": false
							}
						}
					},
					"world": {
						"x": 267,
						"y": 191,
						"width": 64,
						"height": 64,
						"originX": 0.5,
						"originY": 0.5,
						"color": [
							1,
							1,
							1,
							1
						],
						"angle": 0,
						"zElevation": 0
					}
				}
			],
			"sid": 132590015129966,
			"effectTypes": [],
			"isInitiallyVisible": true,
			"isInitiallyInteractive": true,
			"color": [
				1,
				1,
				1,
				1
			],
			"backgroundColor": [
				1,
				1,
				1,
				1
			],
			"isTransparent": true,
			"parallaxX": 1,
			"parallaxY": 1,
			"scaleRate": 1,
			"forceOwnTexture": false,
			"renderingMode": "3d",
			"drawOrder": "z-order",
			"useRenderCells": false,
			"blendMode": "normal",
			"zElevation": 0,
			"global": false
		},
		{
			"name": "ladrillos sombra",
			"overriden": 0,
			"subLayers": [],
			"instances": [
				{
					"type": "SOLIDO_M3",
					"properties": {
						"initially-visible": true,
						"tile-width": 32,
						"tile-height": 32,
						"tile-x-offset": 0,
						"tile-y-offset": 0,
						"tile-x-spacing": 0,
						"tile-y-spacing": 0,
						"tile-x-drawing-offset": 0,
						"tile-y-drawing-offset": 0,
						"drawing-mode": "top-to-right"
					},
					"uid": 9202,
					"instanceVariables": {},
					"behaviors": {
						"Solid": {
							"properties": {
								"enabled": false,
								"tags": ""
							}
						}
					},
					"ownData": {
						"tilemapData": {
							"width": 33,
							"height": 19,
							"max-width": 50,
							"max-height": 27,
							"data": "27x0,19x8,8x0,19x8,8x0,2x8,6,4x9,36,6,6x9,11,3x8,8x0,2x8,13,4x0,3,13,6x0,3,3x8,8x0,2x8,13,4x0,3,13,6x0,3,3x8,8x0,2x8,13,4x0,3,13,6x0,3,3x8,8x0,2x8,13,4x0,3,13,4x0,2,7,15,3x8,8x0,2x8,13,4x0,3,13,2x0,2,7,15,5x8,8x0,2x8,13,4x0,3,13,2x0,4,3x9,11,3x8,8x0,2x8,13,4x0,3,13,6x0,3,3x8,8x0,2x8,13,4x0,3,13,6x0,3,3x8,8x0,2x8,13,4x0,3,13,6x0,3,3x8,8x0,2x8,13,4x0,3,13,6x0,3,3x8,8x0,2x8,13,4x0,3,13,6x0,3,3x8,8x0,2x8,13,3x0,25,3,13,6x0,3,3x8,8x0,2x8,13,4x0,3,13,6x0,3,3x8,8x0,2x8,13,4x0,3,13,6x0,3,3x8,8x0,2x8,13,4x0,3,13,6x0,3,3x8,8x0,2x8,13,4x0,3,13,6x0,3,3x8,8x0,2x8,13,4x0,3,13,6x0,3,3x8,8x0,2x8,13,4x0,3,13,6x0,3,3x8,8x0,2x8,13,4x0,3,13,6x0,3,3x8,8x0,2x8,13,4x0,3,13,6x0,3,3x8,8x0,2x8,13,4x0,4,14,6x0,3,3x8,8x0,2x8,13,12x0,3,3x8,8x0,2x8,13,9x0,2,2x7,15,3x8,8x0,2x8,13,7x0,2,7,15,3x43,3x8,8x0,2x8,13,5x0,2,7,15,5x43,3x8,8x0,2x8,10,5x7,15,7x43,3x8,8x0,19x8,8x0,19x8,8x0,19x8,8x0,2x8,457x0"
						},
						"tile-width": 32,
						"tile-height": 32,
						"tile-x-offset": 0,
						"tile-y-offset": 0,
						"tile-x-spacing": 0,
						"tile-y-spacing": 0
					},
					"world": {
						"x": -90,
						"y": -22,
						"width": 1072,
						"height": 627,
						"originX": 0,
						"originY": 0,
						"color": [
							0,
							0,
							0,
							0.3
						],
						"zElevation": 0
					}
				}
			],
			"sid": 655508613914970,
			"effectTypes": [],
			"isInitiallyVisible": true,
			"isInitiallyInteractive": true,
			"color": [
				1,
				1,
				1,
				1
			],
			"backgroundColor": [
				1,
				1,
				1,
				1
			],
			"isTransparent": true,
			"parallaxX": 1,
			"parallaxY": 1,
			"scaleRate": 1,
			"forceOwnTexture": false,
			"renderingMode": "3d",
			"drawOrder": "z-order",
			"useRenderCells": false,
			"blendMode": "normal",
			"zElevation": 0,
			"global": false
		},
		{
			"name": "Ladrillos",
			"overriden": 0,
			"subLayers": [],
			"instances": [
				{
					"type": "torchFire",
					"properties": {
						"initially-visible": true,
						"initial-animation": "Default",
						"initial-frame": 0,
						"enable-collisions": false,
						"live-preview": false
					},
					"uid": 9203,
					"instanceVariables": {},
					"behaviors": {},
					"world": {
						"x": 468.39602163805864,
						"y": 219.1947287943012,
						"width": 64,
						"height": 32,
						"originX": 0.5,
						"originY": 0.5,
						"color": [
							1,
							1,
							1,
							1
						],
						"angle": 0,
						"zElevation": 0
					}
				},
				{
					"type": "SOLIDO_M3",
					"properties": {
						"initially-visible": true,
						"tile-width": 32,
						"tile-height": 32,
						"tile-x-offset": 0,
						"tile-y-offset": 0,
						"tile-x-spacing": 0,
						"tile-y-spacing": 0,
						"tile-x-drawing-offset": 0,
						"tile-y-drawing-offset": 0,
						"drawing-mode": "top-to-right"
					},
					"uid": 9204,
					"instanceVariables": {},
					"behaviors": {
						"Solid": {
							"properties": {
								"enabled": true,
								"tags": ""
							}
						}
					},
					"ownData": {
						"tilemapData": {
							"width": 33,
							"height": 19,
							"max-width": 50,
							"max-height": 27,
							"data": "27x0,19x8,8x0,19x8,8x0,2x8,6,4x9,11,6,6x9,11,3x8,8x0,2x8,13,4x0,3,13,6x0,3,3x8,8x0,2x8,13,4x0,3,13,6x0,3,3x8,8x0,2x8,13,4x0,3,13,6x0,3,3x8,8x0,2x8,13,4x0,3,13,4x0,2,7,15,3x8,8x0,2x8,13,4x0,3,13,2x0,2,7,15,5x8,8x0,2x8,13,4x0,3,13,2x0,4,3x9,11,3x8,8x0,2x8,13,4x0,3,13,6x0,3,3x8,8x0,2x8,13,4x0,3,13,6x0,3,3x8,8x0,2x8,13,4x0,3,13,6x0,3,3x8,8x0,2x8,13,4x0,3,13,6x0,3,3x8,8x0,2x8,13,4x0,3,13,6x0,3,3x8,8x0,2x8,13,3x0,25,3,13,6x0,3,3x8,8x0,2x8,13,4x0,3,13,6x0,3,3x8,8x0,2x8,13,4x0,3,13,6x0,3,3x8,8x0,2x8,13,4x0,3,13,6x0,3,3x8,8x0,2x8,13,4x0,3,13,6x0,3,3x8,8x0,2x8,13,4x0,3,13,6x0,3,3x8,8x0,2x8,13,4x0,3,13,6x0,3,3x8,8x0,2x8,13,4x0,3,13,6x0,3,3x8,8x0,2x8,13,4x0,3,13,6x0,3,3x8,8x0,2x8,13,4x0,4,14,6x0,3,3x8,8x0,2x8,13,12x0,3,3x8,8x0,2x8,13,9x0,2,2x7,15,3x8,8x0,2x8,13,7x0,2,7,15,3x44,3x8,8x0,2x8,13,5x0,2,7,15,5x44,3x8,8x0,2x8,10,5x7,15,7x44,3x8,8x0,19x8,8x0,19x8,8x0,19x8,8x0,2x8,457x0"
						},
						"tile-width": 32,
						"tile-height": 32,
						"tile-x-offset": 0,
						"tile-y-offset": 0,
						"tile-x-spacing": 0,
						"tile-y-spacing": 0
					},
					"world": {
						"x": -100,
						"y": -32,
						"width": 1072,
						"height": 627,
						"originX": 0,
						"originY": 0,
						"color": [
							1,
							1,
							1,
							1
						],
						"zElevation": 0
					}
				},
				{
					"type": "Inicio_POS",
					"properties": {
						"initially-visible": false,
						"initial-animation": "Default",
						"initial-frame": 0,
						"enable-collisions": true,
						"live-preview": false
					},
					"uid": 9205,
					"instanceVariables": {
						"SIN_animacion_Intro": false,
						"Nivel_1_dificil": false,
						"pos_Y_nueva_lvl_1_dificil": 0
					},
					"behaviors": {},
					"world": {
						"x": 69,
						"y": 358,
						"width": 32,
						"height": 32,
						"originX": 0.5,
						"originY": 0.5,
						"color": [
							1,
							1,
							1,
							1
						],
						"angle": 0,
						"zElevation": 0
					}
				},
				{
					"type": "Gema_currency",
					"properties": {
						"initially-visible": true,
						"initial-animation": "gema",
						"initial-frame": 0,
						"enable-collisions": true,
						"live-preview": false
					},
					"uid": 9206,
					"instanceVariables": {},
					"behaviors": {
						"Sine": {
							"properties": {
								"movement": "vertical",
								"wave": "sine",
								"period": 2,
								"period-random": 0,
								"period-offset": 0,
								"period-offset-random": 0,
								"magnitude": 3,
								"magnitude-random": 0,
								"enabled": true,
								"live-preview": false
							}
						},
						"Tween": {
							"properties": {
								"enabled": true
							}
						}
					},
					"world": {
						"x": 275,
						"y": 369,
						"width": 21,
						"height": 27,
						"originX": 0.5,
						"originY": 0.46296296296296297,
						"color": [
							1,
							1,
							1,
							1
						],
						"angle": 0,
						"zElevation": 0
					}
				},
				{
					"type": "Gema_currency",
					"properties": {
						"initially-visible": true,
						"initial-animation": "gema",
						"initial-frame": 0,
						"enable-collisions": true,
						"live-preview": false
					},
					"uid": 9207,
					"instanceVariables": {},
					"behaviors": {
						"Sine": {
							"properties": {
								"movement": "vertical",
								"wave": "sine",
								"period": 2,
								"period-random": 0,
								"period-offset": 0,
								"period-offset-random": 0,
								"magnitude": 3,
								"magnitude-random": 0,
								"enabled": true,
								"live-preview": false
							}
						},
						"Tween": {
							"properties": {
								"enabled": true
							}
						}
					},
					"world": {
						"x": 416,
						"y": 369,
						"width": 21,
						"height": 27,
						"originX": 0.5,
						"originY": 0.46296296296296297,
						"color": [
							1,
							1,
							1,
							1
						],
						"angle": 0,
						"zElevation": 0
					}
				},
				{
					"type": "Gema_currency",
					"properties": {
						"initially-visible": true,
						"initial-animation": "gema",
						"initial-frame": 0,
						"enable-collisions": true,
						"live-preview": false
					},
					"uid": 9208,
					"instanceVariables": {},
					"behaviors": {
						"Sine": {
							"properties": {
								"movement": "vertical",
								"wave": "sine",
								"period": 2,
								"period-random": 0,
								"period-offset": 0,
								"period-offset-random": 0,
								"magnitude": 3,
								"magnitude-random": 0,
								"enabled": true,
								"live-preview": false
							}
						},
						"Tween": {
							"properties": {
								"enabled": true
							}
						}
					},
					"world": {
						"x": 563,
						"y": 369,
						"width": 21,
						"height": 27,
						"originX": 0.5,
						"originY": 0.46296296296296297,
						"color": [
							1,
							1,
							1,
							1
						],
						"angle": 0,
						"zElevation": 0
					}
				},
				{
					"type": "Gema_currency",
					"properties": {
						"initially-visible": true,
						"initial-animation": "gema",
						"initial-frame": 0,
						"enable-collisions": true,
						"live-preview": false
					},
					"uid": 9209,
					"instanceVariables": {},
					"behaviors": {
						"Sine": {
							"properties": {
								"movement": "vertical",
								"wave": "sine",
								"period": 2,
								"period-random": 0,
								"period-offset": 0,
								"period-offset-random": 0,
								"magnitude": 3,
								"magnitude-random": 0,
								"enabled": true,
								"live-preview": false
							}
						},
						"Tween": {
							"properties": {
								"enabled": true
							}
						}
					},
					"world": {
						"x": 711,
						"y": 369,
						"width": 21,
						"height": 27,
						"originX": 0.5,
						"originY": 0.46296296296296297,
						"color": [
							1,
							1,
							1,
							1
						],
						"angle": 0,
						"zElevation": 0
					}
				},
				{
					"type": "Gema_currency",
					"properties": {
						"initially-visible": true,
						"initial-animation": "gema",
						"initial-frame": 0,
						"enable-collisions": true,
						"live-preview": false
					},
					"uid": 9210,
					"instanceVariables": {},
					"behaviors": {
						"Sine": {
							"properties": {
								"movement": "vertical",
								"wave": "sine",
								"period": 2,
								"period-random": 0,
								"period-offset": 0,
								"period-offset-random": 0,
								"magnitude": 3,
								"magnitude-random": 0,
								"enabled": true,
								"live-preview": false
							}
						},
						"Tween": {
							"properties": {
								"enabled": true
							}
						}
					},
					"world": {
						"x": 158,
						"y": 140,
						"width": 21,
						"height": 27,
						"originX": 0.5,
						"originY": 0.46296296296296297,
						"color": [
							1,
							1,
							1,
							1
						],
						"angle": 0,
						"zElevation": 0
					}
				},
				{
					"type": "Gema_currency",
					"properties": {
						"initially-visible": true,
						"initial-animation": "gema",
						"initial-frame": 0,
						"enable-collisions": true,
						"live-preview": false
					},
					"uid": 9211,
					"instanceVariables": {},
					"behaviors": {
						"Sine": {
							"properties": {
								"movement": "vertical",
								"wave": "sine",
								"period": 2,
								"period-random": 0,
								"period-offset": 0,
								"period-offset-random": 0,
								"magnitude": 3,
								"magnitude-random": 0,
								"enabled": true,
								"live-preview": false
							}
						},
						"Tween": {
							"properties": {
								"enabled": true
							}
						}
					},
					"world": {
						"x": 299,
						"y": 140,
						"width": 21,
						"height": 27,
						"originX": 0.5,
						"originY": 0.46296296296296297,
						"color": [
							1,
							1,
							1,
							1
						],
						"angle": 0,
						"zElevation": 0
					}
				},
				{
					"type": "Gema_currency",
					"properties": {
						"initially-visible": true,
						"initial-animation": "gema",
						"initial-frame": 0,
						"enable-collisions": true,
						"live-preview": false
					},
					"uid": 9212,
					"instanceVariables": {},
					"behaviors": {
						"Sine": {
							"properties": {
								"movement": "vertical",
								"wave": "sine",
								"period": 2,
								"period-random": 0,
								"period-offset": 0,
								"period-offset-random": 0,
								"magnitude": 3,
								"magnitude-random": 0,
								"enabled": true,
								"live-preview": false
							}
						},
						"Tween": {
							"properties": {
								"enabled": true
							}
						}
					},
					"world": {
						"x": 494,
						"y": 141,
						"width": 21,
						"height": 27,
						"originX": 0.5,
						"originY": 0.46296296296296297,
						"color": [
							1,
							1,
							1,
							1
						],
						"angle": 0,
						"zElevation": 0
					}
				},
				{
					"type": "Gema_currency",
					"properties": {
						"initially-visible": true,
						"initial-animation": "gema",
						"initial-frame": 0,
						"enable-collisions": true,
						"live-preview": false
					},
					"uid": 9213,
					"instanceVariables": {},
					"behaviors": {
						"Sine": {
							"properties": {
								"movement": "vertical",
								"wave": "sine",
								"period": 2,
								"period-random": 0,
								"period-offset": 0,
								"period-offset-random": 0,
								"magnitude": 3,
								"magnitude-random": 0,
								"enabled": true,
								"live-preview": false
							}
						},
						"Tween": {
							"properties": {
								"enabled": true
							}
						}
					},
					"world": {
						"x": 618,
						"y": 141,
						"width": 21,
						"height": 27,
						"originX": 0.5,
						"originY": 0.46296296296296297,
						"color": [
							1,
							1,
							1,
							1
						],
						"angle": 0,
						"zElevation": 0
					}
				}
			],
			"sid": 937696916057870,
			"effectTypes": [],
			"isInitiallyVisible": true,
			"isInitiallyInteractive": true,
			"color": [
				1,
				1,
				1,
				1
			],
			"backgroundColor": [
				1,
				1,
				1,
				1
			],
			"isTransparent": true,
			"parallaxX": 1,
			"parallaxY": 1,
			"scaleRate": 1,
			"forceOwnTexture": false,
			"renderingMode": "3d",
			"drawOrder": "z-order",
			"useRenderCells": false,
			"blendMode": "normal",
			"zElevation": 0,
			"global": false
		},
		{
			"name": "ENEMIGOS",
			"overriden": 0,
			"subLayers": [],
			"instances": [
				{
					"type": "llave",
					"properties": {
						"initially-visible": true,
						"initial-animation": "Default",
						"initial-frame": 0,
						"enable-collisions": true,
						"live-preview": false
					},
					"uid": 9214,
					"instanceVariables": {},
					"behaviors": {
						"Sine": {
							"properties": {
								"movement": "horizontal",
								"wave": "sine",
								"period": 4,
								"period-random": 0,
								"period-offset": 0,
								"period-offset-random": 0,
								"magnitude": 50,
								"magnitude-random": 0,
								"enabled": true,
								"live-preview": false
							}
						}
					},
					"world": {
						"x": 813,
						"y": 147,
						"width": 32,
						"height": 32,
						"originX": 0.5,
						"originY": 0.5,
						"color": [
							1,
							1,
							1,
							1
						],
						"angle": 4.712388936179586,
						"zElevation": 0
					}
				},
				{
					"type": "PINCHO",
					"properties": {
						"initially-visible": true,
						"initial-animation": "Default",
						"initial-frame": 0,
						"enable-collisions": true,
						"live-preview": false
					},
					"uid": 9215,
					"instanceVariables": {},
					"behaviors": {
						"Persist": {
							"properties": {}
						}
					},
					"world": {
						"x": 324,
						"y": 436,
						"width": 24,
						"height": 24,
						"originX": 0.5,
						"originY": 0.5,
						"color": [
							1,
							1,
							1,
							1
						],
						"angle": 0,
						"zElevation": 0
					}
				},
				{
					"type": "PINCHO",
					"properties": {
						"initially-visible": true,
						"initial-animation": "Default",
						"initial-frame": 0,
						"enable-collisions": true,
						"live-preview": false
					},
					"uid": 9216,
					"instanceVariables": {},
					"behaviors": {
						"Persist": {
							"properties": {}
						}
					},
					"world": {
						"x": 349,
						"y": 436,
						"width": 24,
						"height": 24,
						"originX": 0.5,
						"originY": 0.5,
						"color": [
							1,
							1,
							1,
							1
						],
						"angle": 0,
						"zElevation": 0
					}
				},
				{
					"type": "PINCHO",
					"properties": {
						"initially-visible": true,
						"initial-animation": "Default",
						"initial-frame": 0,
						"enable-collisions": true,
						"live-preview": false
					},
					"uid": 9217,
					"instanceVariables": {},
					"behaviors": {
						"Persist": {
							"properties": {}
						}
					},
					"world": {
						"x": 468,
						"y": 436,
						"width": 24,
						"height": 24,
						"originX": 0.5,
						"originY": 0.5,
						"color": [
							1,
							1,
							1,
							1
						],
						"angle": 0,
						"zElevation": 0
					}
				},
				{
					"type": "PINCHO",
					"properties": {
						"initially-visible": true,
						"initial-animation": "Default",
						"initial-frame": 0,
						"enable-collisions": true,
						"live-preview": false
					},
					"uid": 9218,
					"instanceVariables": {},
					"behaviors": {
						"Persist": {
							"properties": {}
						}
					},
					"world": {
						"x": 492,
						"y": 436,
						"width": 24,
						"height": 24,
						"originX": 0.5,
						"originY": 0.5,
						"color": [
							1,
							1,
							1,
							1
						],
						"angle": 0,
						"zElevation": 0
					}
				},
				{
					"type": "PINCHO",
					"properties": {
						"initially-visible": true,
						"initial-animation": "Default",
						"initial-frame": 0,
						"enable-collisions": true,
						"live-preview": false
					},
					"uid": 9219,
					"instanceVariables": {},
					"behaviors": {
						"Persist": {
							"properties": {}
						}
					},
					"world": {
						"x": 628,
						"y": 436,
						"width": 24,
						"height": 24,
						"originX": 0.5,
						"originY": 0.5,
						"color": [
							1,
							1,
							1,
							1
						],
						"angle": 0,
						"zElevation": 0
					}
				},
				{
					"type": "PINCHO",
					"properties": {
						"initially-visible": true,
						"initial-animation": "Default",
						"initial-frame": 0,
						"enable-collisions": true,
						"live-preview": false
					},
					"uid": 9220,
					"instanceVariables": {},
					"behaviors": {
						"Persist": {
							"properties": {}
						}
					},
					"world": {
						"x": 652,
						"y": 436,
						"width": 24,
						"height": 24,
						"originX": 0.5,
						"originY": 0.5,
						"color": [
							1,
							1,
							1,
							1
						],
						"angle": 0,
						"zElevation": 0
					}
				},
				{
					"type": "Enemigo_piedra",
					"properties": {
						"initially-visible": true,
						"initial-animation": "cierra_ojos",
						"initial-frame": 0,
						"enable-collisions": true,
						"live-preview": false
					},
					"uid": 9221,
					"instanceVariables": {
						"CONTADOR": 0,
						"VELOCIDAD": 5.5,
						"ESTADO": "arriba_espera",
						"tiempo_arriba": 25,
						"espera_abajo": 40
					},
					"behaviors": {},
					"world": {
						"x": 554,
						"y": 97,
						"width": 64,
						"height": 64,
						"originX": 0.5,
						"originY": 0.5,
						"color": [
							1,
							1,
							1,
							1
						],
						"angle": 0,
						"zElevation": 0
					}
				},
				{
					"type": "Black_ball",
					"properties": {
						"initially-visible": true,
						"initial-animation": "Default",
						"initial-frame": 0,
						"enable-collisions": true,
						"live-preview": false
					},
					"uid": 9222,
					"instanceVariables": {
						"direccion": 1,
						"time_scale": 0.6,
						"activa_TOPES": true,
						"IZQ_tope": 230,
						"DER_tope": 725
					},
					"behaviors": {
						"Platform": {
							"properties": {
								"max-speed": 280,
								"acceleration": 3000,
								"deceleration": 3000,
								"jump-strength": 750,
								"gravity": 1800,
								"max-fall-speed": 500,
								"double-jump": false,
								"jump-sustain": 0,
								"default-controls": false,
								"enabled": true
							}
						}
					},
					"world": {
						"x": 294,
						"y": 301,
						"width": 36,
						"height": 36,
						"originX": 0.548781,
						"originY": 0.529412,
						"color": [
							1,
							1,
							1,
							1
						],
						"angle": 0,
						"zElevation": 0
					}
				}
			],
			"sid": 700511401760849,
			"effectTypes": [],
			"isInitiallyVisible": true,
			"isInitiallyInteractive": true,
			"color": [
				1,
				1,
				1,
				1
			],
			"backgroundColor": [
				1,
				1,
				1,
				1
			],
			"isTransparent": true,
			"parallaxX": 1,
			"parallaxY": 1,
			"scaleRate": 1,
			"forceOwnTexture": false,
			"renderingMode": "3d",
			"drawOrder": "z-order",
			"useRenderCells": false,
			"blendMode": "normal",
			"zElevation": 0,
			"global": false
		},
		{
			"name": "pelota",
			"overriden": 0,
			"subLayers": [],
			"instances": [
				{
					"type": "bola",
					"properties": {
						"initially-visible": true,
						"initial-animation": "DERECHA_4",
						"initial-frame": 0,
						"enable-collisions": true,
						"live-preview": false
					},
					"uid": 9223,
					"instanceVariables": {
						"tiempo_dash": 0
					},
					"behaviors": {
						"Platform": {
							"properties": {
								"max-speed": 250,
								"acceleration": 1500,
								"deceleration": 1500,
								"jump-strength": 550,
								"gravity": 1500,
								"max-fall-speed": 1000,
								"double-jump": false,
								"jump-sustain": 0,
								"default-controls": false,
								"enabled": true
							}
						},
						"Pin": {
							"properties": {
								"destroy": false
							}
						}
					},
					"world": {
						"x": 69.612548828,
						"y": 349.635162354,
						"width": 36.4,
						"height": 30.16,
						"originX": 0.5714285714285714,
						"originY": 0.5,
						"color": [
							1,
							1,
							1,
							1
						],
						"angle": 0,
						"zElevation": 0
					}
				}
			],
			"sid": 204727528991330,
			"effectTypes": [],
			"isInitiallyVisible": true,
			"isInitiallyInteractive": true,
			"color": [
				1,
				1,
				1,
				1
			],
			"backgroundColor": [
				1,
				1,
				1,
				1
			],
			"isTransparent": true,
			"parallaxX": 1,
			"parallaxY": 1,
			"scaleRate": 1,
			"forceOwnTexture": false,
			"renderingMode": "3d",
			"drawOrder": "z-order",
			"useRenderCells": false,
			"blendMode": "normal",
			"zElevation": 0,
			"global": false
		},
		{
			"name": "VIDAS",
			"overriden": 0,
			"subLayers": [],
			"instances": [],
			"sid": 629905860008722,
			"effectTypes": [],
			"isInitiallyVisible": true,
			"isInitiallyInteractive": true,
			"color": [
				1,
				1,
				1,
				1
			],
			"backgroundColor": [
				1,
				1,
				1,
				1
			],
			"isTransparent": true,
			"parallaxX": 0,
			"parallaxY": 0,
			"scaleRate": 1,
			"forceOwnTexture": false,
			"renderingMode": "3d",
			"drawOrder": "z-order",
			"useRenderCells": false,
			"blendMode": "normal",
			"zElevation": 0,
			"global": false
		},
		{
			"name": "HUD",
			"overriden": 0,
			"subLayers": [],
			"instances": [
				{
					"type": "left_BTN",
					"properties": {
						"initially-visible": false,
						"initial-animation": "Default",
						"initial-frame": 0,
						"enable-collisions": true,
						"live-preview": false
					},
					"uid": 9224,
					"instanceVariables": {},
					"behaviors": {},
					"world": {
						"x": 1.379211426,
						"y": 438.985656738,
						"width": 137.414291382,
						"height": 86.009368896,
						"originX": 1,
						"originY": 0.5,
						"color": [
							1,
							1,
							1,
							1
						],
						"angle": 0,
						"zElevation": 0
					}
				},
				{
					"type": "left_BTN2",
					"properties": {
						"initially-visible": false,
						"initial-animation": "Default",
						"initial-frame": 0,
						"enable-collisions": true,
						"live-preview": false
					},
					"uid": 9225,
					"instanceVariables": {},
					"behaviors": {},
					"world": {
						"x": -129,
						"y": 311,
						"width": 137.413970947,
						"height": 86.009597778,
						"originX": 0,
						"originY": 0.5,
						"color": [
							1,
							1,
							1,
							1
						],
						"angle": 0,
						"zElevation": 0
					}
				}
			],
			"sid": 424560373557067,
			"effectTypes": [],
			"isInitiallyVisible": true,
			"isInitiallyInteractive": true,
			"color": [
				1,
				1,
				1,
				1
			],
			"backgroundColor": [
				1,
				1,
				1,
				1
			],
			"isTransparent": true,
			"parallaxX": 0,
			"parallaxY": 0,
			"scaleRate": 1,
			"forceOwnTexture": false,
			"renderingMode": "3d",
			"drawOrder": "z-order",
			"useRenderCells": false,
			"blendMode": "normal",
			"zElevation": 0,
			"global": false
		},
		{
			"name": "salida",
			"overriden": 0,
			"subLayers": [],
			"instances": [],
			"sid": 878049056151186,
			"effectTypes": [],
			"isInitiallyVisible": true,
			"isInitiallyInteractive": true,
			"color": [
				1,
				1,
				1,
				1
			],
			"backgroundColor": [
				1,
				1,
				1,
				1
			],
			"isTransparent": true,
			"parallaxX": 1,
			"parallaxY": 1,
			"scaleRate": 1,
			"forceOwnTexture": false,
			"renderingMode": "3d",
			"drawOrder": "z-order",
			"useRenderCells": false,
			"blendMode": "normal",
			"zElevation": 0,
			"global": false
		}
	],
	"sid": 708327183553141,
	"nonworld-instances": [],
	"effectTypes": [],
	"width": 854,
	"height": 480,
	"unboundedScrolling": true,
	"vpX": 0.5,
	"vpY": 0.5,
	"projection": "perspective",
	"eventSheet": "juego_evento"
}